DMU/__init__.py
DMU/custom_logger.py
DMU/graph_styles.py
DMU/lumutils.py
DMU/plot_utils.py
DMU/sem_tools.py
DMU/utils.py
DMU/utils_utils.py
dmu-0.4.0.dist-info/licenses/LICENSE
dmu-0.4.0.dist-info/METADATA
dmu-0.4.0.dist-info/WHEEL
dmu-0.4.0.dist-info/top_level.txt
dmu-0.4.0.dist-info/RECORD
