Metadata-Version: 2.4
Name: DMU
Version: 0.4.0
Summary: This package is used to store commonly used functions on pip for the sake of easy pulling for other code. Features utilities for IV characterisation, lumerical data analysis and geometry instanciation, SEM stitching and other tools.
Home-page: https://github.com/DeltaMod/DMU
Author: Atli Vidar Már FLodgren
Author-email: vidar@flodgren.com
Keywords: hello world example examples
Classifier: Programming Language :: Python :: 3
Classifier: License :: OSI Approved :: GNU General Public License v3 (GPLv3)
Classifier: Operating System :: OS Independent
Classifier: Development Status :: 2 - Pre-Alpha
License-File: LICENSE
Requires-Dist: csv
Requires-Dist: json
Requires-Dist: mat73
Requires-Dist: sys
Requires-Dist: numpy
Requires-Dist: utils_utils
Requires-Dist: plot_utils
Requires-Dist: scipy
Requires-Dist: h5py
Requires-Dist: natsort
Requires-Dist: custom_logger
Requires-Dist: time
Requires-Dist: os
Requires-Dist: xlrd
Requires-Dist: pickle
Requires-Dist: matplotlib
Requires-Dist: mpl_toolkits
Requires-Dist: tkinter
Requires-Dist: collections
Requires-Dist: docutils>=0.3
Dynamic: author
Dynamic: author-email
Dynamic: classifier
Dynamic: description
Dynamic: description-content-type
Dynamic: home-page
Dynamic: keywords
Dynamic: license-file
Dynamic: requires-dist
Dynamic: summary
